sedkit/__init__.py
sedkit/catalog.py
sedkit/helpers.py
sedkit/isochrone.py
sedkit/mcmc.py
sedkit/modelgrid.py
sedkit/query.py
sedkit/relations.py
sedkit/sed.py
sedkit/spectrum.py
sedkit/uncertainties.py
sedkit/utilities.py
sedkit/data/AFGK_radii.txt
sedkit/data/L3_photometry.txt
sedkit/data/L3_spectrum.fits
sedkit/data/README.rst
sedkit/data/STScI_Vega.txt
sedkit/data/Trappist-1_NIR.fits
sedkit/data/Trappist-1_OPT.fits
sedkit/data/coords.txt
sedkit/data/dwarf_sequence.txt
sedkit/data/sources.txt
sedkit/data/figures/Lbol_v_SpT.png
sedkit/data/figures/Lbol_v_mass.png
sedkit/data/figures/sed_plot.png
sedkit/data/models/atmospheric/spexprismlibrary/index.p
sedkit/data/models/atmospheric/spexprismlibrary/spex-prism_2MASPJ0345432+254023_20030905_BUR06B.txt.xml
sedkit/data/models/atmospheric/spexprismlibrary/spex-prism_2MASSIJ0103320+193536_20030919_CRU04A.txt.xml
sedkit/data/models/atmospheric/spexprismlibrary/spex-prism_2MASSIJ0415195-093506_20030917_BUR04B.txt.xml
sedkit/data/models/atmospheric/spexprismlibrary/spex-prism_2MASSIJ0727182+171001_20040310_BUR06D.txt.xml
sedkit/data/models/atmospheric/spexprismlibrary/spex-prism_2MASSIJ1010148-040649_20050324_REI06A.txt.xml
sedkit/data/models/atmospheric/spexprismlibrary/spex-prism_2MASSIJ2254188+312349_20030918_BUR04B.txt.xml
sedkit/data/models/atmospheric/spexprismlibrary/spex-prism_2MASSJ12095613-1004008_20030523_BUR04B.txt.xml
sedkit/data/models/atmospheric/spexprismlibrary/spex-prism_2MASSJ15031961+2525196_20030522_BUR04B.txt.xml
sedkit/data/models/atmospheric/spexprismlibrary/spex-prism_2MASSJ21580457-1550098_20070927_KIR10A.txt.xml
sedkit/data/models/atmospheric/spexprismlibrary/spex-prism_2MASSWJ1146345+223053_20080112_BUR10A.txt.xml
sedkit/data/models/atmospheric/spexprismlibrary/spex-prism_2MASSWJ1439284+192915_20030523_BUR04B.txt.xml
sedkit/data/models/atmospheric/spexprismlibrary/spex-prism_2MASSWJ1506544+132106_20060410_BUR07C.txt.xml
sedkit-2.1.dist-info/LICENSE
sedkit-2.1.dist-info/METADATA
sedkit-2.1.dist-info/WHEEL
sedkit-2.1.dist-info/top_level.txt
sedkit-2.1.dist-info/RECORD
