Metadata-Version: 2.2
Name: sedkit
Version: 2.1
Summary: Spectral energy distribution construction and analysis tools
Author: Sherelyn Alejandro Merchan
Author-email: Joe Filippazzo <jfilippazzo@stsci.edu>
Maintainer-email: Kelle Cruz <kellecruz@gmail.com>
Keywords: astronomy
Classifier: Intended Audience :: Science/Research
Classifier: Operating System :: OS Independent
Classifier: License :: OSI Approved :: BSD License
Classifier: Programming Language :: Python :: 3
Classifier: Topic :: Scientific/Engineering :: Astronomy
Classifier: Topic :: Software Development :: Libraries :: Python Modules
Requires-Python: >=3.11
License-File: LICENSE
Requires-Dist: astropy>=6.1.3
Requires-Dist: astroquery>=0.4.7
Requires-Dist: astropy>=6.1.3
Requires-Dist: astroquery>=0.4.7
Requires-Dist: bokeh>=3.2.1
Requires-Dist: dill>=0.3.4
Requires-Dist: dustmaps>=1.0.13
Requires-Dist: emcee>=3.1.6
Requires-Dist: numpy>=2.1
Requires-Dist: pandas>=2.2.2
Requires-Dist: scipy>=1.14.1
Requires-Dist: svo-filters>=0.4.4
Requires-Dist: setuptools>=64
Provides-Extra: test
Requires-Dist: pytest; extra == "test"
